QuantPlasia/QuantPlasia.py
QuantPlasia/__init__.py
QuantPlasia/data/Cell Signatures/GSEA_output.tsv
QuantPlasia/data/Extent of Differentiation/Collapsed_Probes.tsv
QuantPlasia/data/Extent of Differentiation/DiGeSt.txt
QuantPlasia/data/Extent of Differentiation/GSEA_LEA_Output.xlsx
QuantPlasia/data/Extent of Differentiation/GSEA_LEA_Output_COAD.xlsx
QuantPlasia-0.2.5.dist-info/METADATA
QuantPlasia-0.2.5.dist-info/WHEEL
QuantPlasia-0.2.5.dist-info/top_level.txt
QuantPlasia-0.2.5.dist-info/RECORD
