Metadata-Version: 2.1
Name: QuantPlasia
Version: 0.2.5
Summary: Metaplasia Quantification Tool
Maintainer-email: Pravallika Govada <pravallika2606g@gmail.com>
License: BSD-2-Clause
Requires-Python: >=3.9
Requires-Dist: pandas>=1.0.0
Requires-Dist: openpyxl>=3.0.0
